Metadata-Version: 1.0
Name: dashboards-navigation-burger
Version: 0.0.1
Summary: A burger button to be used to toggle the appearance and disapperance of the navigation barr
Home-page: UNKNOWN
Author: Zeke Ayonrinde zeke.ayonrinde@15gifts.com
Author-email: UNKNOWN
License: MIT
Platform: UNKNOWN
